[
  {
    "url": "https://x.com/todoroki_hajime/status/0000000000000000000",
    "date": "2026-06-08",
    "text": {
      "zh": "（範例，請替換）番長看到大家的生日應援了！謝謝やたてぃ学園はじめラ部跟所有真っす組⚡ 把這裡換成はじめ實際回信／引用轉推的內容，右下角連回原推文。",
      "ja": "（サンプル・要差し替え）番長、みんなの誕生日応援を見たぞ！やたてぃ学園はじめラ部とすべての真っす組に感謝⚡ ここをはじめ本人の返信・引用ポストの内容に差し替えて、右下から原ポストへリンクします。",
      "en": "(Sample — please replace) The Bancho saw everyone's birthday support! Thank you, Yataty Gakuen Hajime Rabu and all of Massugu-gumi. Replace this with Hajime's actual reply/quote post; the link bottom-right goes to the original."
    }
  }
]
